README.md
setup.cfg
setup.py
xcalc/__init__.py
xcalc/xcalc.py
xcalc.egg-info/PKG-INFO
xcalc.egg-info/SOURCES.txt
xcalc.egg-info/dependency_links.txt
xcalc.egg-info/not-zip-safe
xcalc.egg-info/top_level.txt