Metadata-Version: 2.1
Name: xcalc
Version: 1.1.2
Summary: simple calculator
Author-email: m1rza.ismailov@yandex.ru
